potions_rt-0.1.0.dist-info/METADATA
potions_rt-0.1.0.dist-info/WHEEL
potions_rt/__init__.py
potions_rt/hydro_results.py
potions_rt/objective_functions.py
potions_rt/reactive_transport_results.py
potions_rt/py.typed
potions_rt/_potions_rt.pyi
potions_rt/_potions_rt.abi3.so
potions_rt-0.1.0.dist-info/RECORD
